{"name":"蒋超","number":"21010224","college":"交通学院","style":"学术影响力","proof":" 1：2010-2011学年国家奖学金；` 2：2012-2013学年苏交科奖学金；` 3：2010-2011学年校三好学生；` 4：2013年东南大学学习优秀生；` 5：2011-2012学年交通学院优秀学生干部；` 6：2012-2013学年交通学院学生会研学部部长；` 7：校高数竞赛二等奖；` 8：校数模竞赛二等奖；` 9：校力学竞赛一等奖；` 10：“矿大杯”第八届江苏省大学生力学竞赛特等奖，全省第2名；` 11：第九届全国周培源大学生力学竞赛一等奖，团体赛优胜奖；` 12：全国英语竞赛二等奖；`","introduce":"尊敬的各位老师、同学：`   大家好！我叫蒋超，来自交通学院10级道桥茅以升班，很荣幸能有机会来竞选东南大学2014最具影响力毕业生，我认为这是对东南人最崇高的荣誉。影响力是用乐于接受的方式，改变他人的思想和行动的能力，而我认为大学四年间，在学术上和学生工作中，我都以我的热情、态度、理念，影响着周围许多人的大学生活。`   在学术上，4年间我取得了让自己很满意的成果。从一入学就顺利进入茅以升班，再到大一年级总排第2名，再到后来专业一直保持前三之列，保研总排名专业第一，学习上一贯认真专注的我四年来顺风顺水。`   除单纯的专业学习，不想当一个死读书的学霸的我还热衷于参加各类竞赛，不仅因为能提高实践运用能力，更是因为有挑战有合作有拼搏。在竞赛方面，我获得过校高数竞赛二等奖，校数模竞赛二等奖，校英语竞赛一等奖，校力学竞赛一等奖。此外，我还获得过江苏省力学竞赛特等奖，全国周培源力学竞赛一等奖，全国英语竞赛二等奖。印象最深刻的是数模竞赛、力学竞赛以及未拿奖的土木学院的结构竞赛，因为这些背后是我和同学一起熬夜计算模型，是教室中为了目标做一道又一道的题，是几个人想创意砍木条拼结构的日日夜夜。`   学生工作上，一进入大学，我就参加了院学生会和艺术团，希望锻炼工作组织能力，结交更多的人，因为我一直觉得做人做事远比学习更重要。学生会的每一年都锻炼了我很多，大一作为秘书处一名理事，为院各类学生活动做准备工作，期间还参加了智联招聘，挤出时间张贴海报发送传单，做各公司的现场；大二，我担任了研学部的部长，作为院学生会新增的部门，当时的我备感责任重大。大二一年，我组织过多次课外研学讲座，其中不乏院士参加，还组织过校交通科技大赛，协助完成第七届全国交通科技大赛的举办。各项赛事、讲座、活动的举办不仅让我做事更细心周全，考虑全面，更锻炼了我与他人协作，带领团队完成任务，沟通交流的能力。学生会的点点滴滴，组成了我大学中最美好的回忆。`   我有我的想法与目标，于是我会为了它执着地迈出步伐，我并没那么聪明，我只是想干的希望的执着着要干好。如果我有着那么些影响，我希望就是这些。每个人都有目标，我只是执着的一直走在路上。"}