{"realname":"程莹","number":"43209109","college":"医学院","style":"公益影响力","proof":"担任职务：`1、2012.08~2013.10担任“东南大学社区健康教育志愿团”团长`2、2012.08~2013.08担任“东南大学丁家桥文化素质教育中心”学生处总负责人```荣誉及奖励：`1、获“2013本科生公派留学项目”资格，赴在德国汉堡大学医学中心UKE泌尿外科和普外科实习；`2、获得“2012年优秀本科生推荐出国交流”资格（日本爱知工业大学，由于两国政治原因未成行）；`3、负责项目“国家级大学生创新性实验项目”（编号：111028659）评为优秀；`4、“东南大学第四届医学生临床技能竞赛”校级一等奖；`5、东南大学首届遗传工程机器设计竞赛暨“国际遗传工程机器设计竞赛（iGEM ）”选拔赛荣获校级第二名；`6、医学机能实验学实验操作技能竞赛荣获院级一等奖第一名；`7、荣获“文化素质教育优秀实践奖”；`8、2009—2010学年被评为“东南大学三好学生”。`","introduce":"  童年的记忆大多与爷爷的乡下小诊所有关，爷爷有老慢支，每给病人打针后，都会痛苦地喘息。我很疑惑：“爷爷自己是医生，为什么不治自己？”长大后慢慢地理解了：慢性病是就是这样，慢慢地折磨着你老去。从那时起，“慢性病”便成了让我极其憎恶的字眼。`  冥冥之中，我继承了爷爷的衣钵，踏上了医学之路。大二那年我去社区做志愿者，一位奶奶跟我抱怨血糖不稳定，吃药也没得好。临走前，老奶奶那句“我要被这病折磨到死为止了”让我的心不禁一颤：“慢性病。”也许就是从那刻开始，我内心低吼着：挣脱“慢性病”这个枷锁的束缚！身为一个未来的医生，我等不及到自己羽翼丰满地时候再做抗争，现在就该有所行动。那年秋天，我参加了由东南大学社区健康教育志愿团组织的“联合国糖尿病日——环湖行”活动，一路上，我们的宣传横幅和口号引来不少人驻足。看着自己微乎其微的努力竟然得到了回应，内心激动万分，成就感瞬间爆棚。那年，我加入了这个与“糖尿病”做抗争的志愿团。`  初入团时，志愿团正协助对南京各社区进行糖尿病免费筛查。在筛查中，我明显感受到一些不正规的医疗广告给病急乱投医的糖尿病患者灌输了很多不正确的知识。我积极报名了社区宣教员考聘会，被选拔为社区宣教员。每年的“糖尿病规范注射日”，“世界糖尿病日”，我们走进社区，组织宣讲、义诊等一系列活动。我喜欢自己的双重角色：医学生和志愿者。在学校，我自己在不断接受新的医学知识；在社区，我又将自己所学的知识传播给那些深受糖尿病折磨的人。我在付出，也一直在成长。这一年里，我志愿服务的热情得到了团里的关注，在志愿团五周年庆典上，我被提升为团长。在所有团员的共同努力下，志愿团由共青团江苏省委正式命名为“江苏省青年志愿者服务基地”。`  去年4月南京同伴支持项目启动。借鉴国际同伴支持理念，融入志愿服务精神，探索“医院-社区-患者-志愿者”四位一体的慢性病管理模式。志愿团大胆创新，打破传统的讲座模式，寓教于乐，手绘健康操图谱，发行健康教育报。通过做饭比赛等游戏传播糖尿病饮食知识；关于糖尿病足，患者们在课堂上边洗脚边学习；运动课堂则遍布南京名胜。去年10月，志愿团项目“中国慢性病防治“四位一体”管理模式的探索-基于南京九社区老年糖尿病患者模式调查与服务实践”获得第13届大挑特等奖。`  四年了，志愿团增添了一批又一批的新面孔，我这张“老脸”也是时候隐去了。这个夏天，志愿团又会有多少新面孔呢？ "}